sms_message_aws_sns_local/__init__.py
sms_message_aws_sns_local/sms_message_aws_sns.py
sms_message_aws_sns_local-0.0.40.dist-info/METADATA
sms_message_aws_sns_local-0.0.40.dist-info/WHEEL
sms_message_aws_sns_local-0.0.40.dist-info/top_level.txt
sms_message_aws_sns_local-0.0.40.dist-info/RECORD
