Metadata-Version: 2.1
Name: sms-message-aws-sns-local
Version: 0.0.40
Summary: PyPI Package for Circles AWS SMS
Home-page: https://github.com/circles-zone/sms-message-aws-sns-local-python-package
Author: Circles
Author-email: info@circlez.ai
Classifier: Programming Language :: Python :: 3
Classifier: License :: Other/Proprietary License
Classifier: Operating System :: OS Independent
Requires-Dist: boto3 >=1.28.70
Requires-Dist: logger-local >=0.0.135
Requires-Dist: message-local >=0.0.123
Requires-Dist: database-mysql-local >=0.0.290
Requires-Dist: python-sdk-remote >=0.0.93
